odoo/addons/shopfloor_location_content_transfer_force_package/README.rst
odoo/addons/shopfloor_location_content_transfer_force_package/__init__.py
odoo/addons/shopfloor_location_content_transfer_force_package/__manifest__.py
odoo/addons/shopfloor_location_content_transfer_force_package/i18n/shopfloor_location_content_transfer_force_package.pot
odoo/addons/shopfloor_location_content_transfer_force_package/readme/CONTRIBUTORS.rst
odoo/addons/shopfloor_location_content_transfer_force_package/readme/DESCRIPTION.rst
odoo/addons/shopfloor_location_content_transfer_force_package/services/__init__.py
odoo/addons/shopfloor_location_content_transfer_force_package/services/location_content_transfer.py
odoo/addons/shopfloor_location_content_transfer_force_package/static/description/icon.png
odoo/addons/shopfloor_location_content_transfer_force_package/static/description/index.html
odoo/addons/shopfloor_location_content_transfer_force_package/tests/__init__.py
odoo/addons/shopfloor_location_content_transfer_force_package/tests/test_location_content_transfer_force_package.py
odoo14_addon_shopfloor_location_content_transfer_force_package-14.0.1.1.0.dist-info/METADATA
odoo14_addon_shopfloor_location_content_transfer_force_package-14.0.1.1.0.dist-info/WHEEL
odoo14_addon_shopfloor_location_content_transfer_force_package-14.0.1.1.0.dist-info/top_level.txt
odoo14_addon_shopfloor_location_content_transfer_force_package-14.0.1.1.0.dist-info/RECORD
